setup.py
django_clickbank/__init__.py
django_clickbank/admin.py
django_clickbank/forms.py
django_clickbank/models.py
django_clickbank/settings.py
django_clickbank/signals.py
django_clickbank/urls.py
django_clickbank/views.py
django_clickbank.egg-info/PKG-INFO
django_clickbank.egg-info/SOURCES.txt
django_clickbank.egg-info/dependency_links.txt
django_clickbank.egg-info/top_level.txt
django_clickbank/migrations/0001_initial.py
django_clickbank/migrations/0002_auto__add_index_notification_receipt__chg_field_notification_next_paym.py
django_clickbank/migrations/0003_auto__add_field_notification_rebill_parent_receipt__del_unique_notific.py
django_clickbank/migrations/__init__.py
django_clickbank/tests/__init__.py
django_clickbank/tests/posts.py
django_clickbank/tests/test_helpers.py
django_clickbank/tests/test_views.py
django_clickbank/util/__init__.py
django_clickbank/util/exceptions.py
django_clickbank/util/helpers.py