Metadata-Version: 1.1
Name: django-clickbank
Version: 0.2.5
Summary: A pluggable application for receiving data from ClickBank's Instant Payment Notifications
Home-page: https://github.com/sureiya/django-clickbank/
Author: Chris Modjeska
Author-email: kin@remuria.net
License: MIT
Keywords: django clickbank ipn
Platform: UNKNOWN
Classifier: Framework :: Django
Classifier: Intended Audience :: Developers
Classifier: Intended Audience :: System Administrators
Classifier: Operating System :: OS Independent
Classifier: Topic :: Software Development
Classifier: Programming Language :: Python :: 2.7
